[{"mp_id":35904,"twitter_handle":"HonEdFast","word_cloud":"autoimg/wordcloud-pol/ed-fast.png","favourite_word":"ukraine"},{"mp_id":71482,"twitter_handle":"RomeoSaganash","word_cloud":"autoimg/wordcloud-pol/romeo-saganash.png","favourite_word":"first"},{"mp_id":232,"twitter_handle":"MooreNpd","word_cloud":"autoimg/wordcloud-pol/christine-moore.png","favourite_word":"problem"},{"mp_id":88350,"twitter_handle":"sergecormierlib","word_cloud":null,"favourite_word":"marine"},{"mp_id":88384,"twitter_handle":"melaniejoly","word_cloud":null,"favourite_word":"colleague"},{"mp_id":25508,"twitter_handle":"markhollandlib","word_cloud":null,"favourite_word":"process"},{"mp_id":71337,"twitter_handle":"AngeloIacono","word_cloud":null,"favourite_word":"chair"},{"mp_id":31289,"twitter_handle":"CarolHughesMP","word_cloud":"autoimg/wordcloud-pol/carol-hughes.png","favourite_word":"conservatives"},{"mp_id":88394,"twitter_handle":"stephanelauzon5","word_cloud":null,"favourite_word":"speech"},{"mp_id":88671,"twitter_handle":"LeonaAlleslev","word_cloud":null,"favourite_word":"post"},{"mp_id":88283,"twitter_handle":"avalonMPKen","word_cloud":null,"favourite_word":"ill"},{"mp_id":88397,"twitter_handle":"Remi_Masse1","word_cloud":null,"favourite_word":"help"},{"mp_id":59235,"twitter_handle":"BlakeRichardsMP","word_cloud":"autoimg/wordcloud-pol/blake-richards.png","favourite_word":"obviously"},{"mp_id":88674,"twitter_handle":"JohnBrassardCPC","word_cloud":null,"favourite_word":"liberals"},{"mp_id":88679,"twitter_handle":null,"word_cloud":null,"favourite_word":"liberal"},{"mp_id":1832,"twitter_handle":"KevinASorenson","word_cloud":"autoimg/wordcloud-pol/kevin-sorenson.png","favourite_word":"tax"},{"mp_id":1209,"twitter_handle":"GerryRitzMP","word_cloud":"autoimg/wordcloud-pol/gerry-ritz.png","favourite_word":"farmers"},{"mp_id":88683,"twitter_handle":"NeilREllis","word_cloud":null,"favourite_word":null},{"mp_id":88687,"twitter_handle":"beynate","word_cloud":null,"favourite_word":"respect"},{"mp_id":35309,"twitter_handle":"MaximeBernier","word_cloud":"autoimg/wordcloud-pol/maxime-bernier.png","favourite_word":"money"},{"mp_id":35320,"twitter_handle":"SBoucherMP","word_cloud":null,"favourite_word":"liberals"},{"mp_id":88404,"twitter_handle":"Alupa_Clarke","word_cloud":null,"favourite_word":"measures"},{"mp_id":1813,"twitter_handle":null,"word_cloud":"autoimg/wordcloud-pol/dominic-leblanc.png","favourite_word":"colleagues"},{"mp_id":413,"twitter_handle":null,"word_cloud":"autoimg/wordcloud-pol/louis-plamondon.png","favourite_word":"quebec"},{"mp_id":35389,"twitter_handle":"StevenBlaneyPCC","word_cloud":"autoimg/wordcloud-pol/steven-blaney.png","favourite_word":"protect"},{"mp_id":71368,"twitter_handle":"MattDube","word_cloud":"autoimg/wordcloud-pol/matthew-dube.png","favourite_word":"colleague"},{"mp_id":71357,"twitter_handle":"RE_Brosseau","word_cloud":"autoimg/wordcloud-pol/ruth-ellen-brosseau.png","favourite_word":"farmers"},{"mp_id":58519,"twitter_handle":"JudyFooteMP","word_cloud":"autoimg/wordcloud-pol/judy-foote.png","favourite_word":"conservative"},{"mp_id":84660,"twitter_handle":"EmmanuelDubourg","word_cloud":null,"favourite_word":"conservatives"},{"mp_id":89109,"twitter_handle":"MartinBowRiver","word_cloud":null,"favourite_word":"air"},{"mp_id":88692,"twitter_handle":"sangharamesh","word_cloud":null,"favourite_word":"unions"},{"mp_id":88694,"twitter_handle":"RajLiberal","word_cloud":null,"favourite_word":"infrastructure"},{"mp_id":88698,"twitter_handle":"MPRubySahota","word_cloud":null,"favourite_word":"citizenship"},{"mp_id":88703,"twitter_handle":"SoniaLiberal","word_cloud":null,"favourite_word":"need"},{"mp_id":88705,"twitter_handle":"KamalKheraLib","word_cloud":null,"favourite_word":"dementia"},{"mp_id":7251,"twitter_handle":"LarryMaguireMP","word_cloud":null,"favourite_word":"well"},{"mp_id":35539,"twitter_handle":"Phil4Brant","word_cloud":"autoimg/wordcloud-pol/phil-mccoleman.png","favourite_word":"finance"},{"mp_id":198,"twitter_handle":"DenisParadisPLC","word_cloud":null,"favourite_word":"riding"},{"mp_id":58621,"twitter_handle":"AlexandraBrStL","word_cloud":null,"favourite_word":"chair"},{"mp_id":25522,"twitter_handle":"LarryMillerMP","word_cloud":"autoimg/wordcloud-pol/larry-miller.png","favourite_word":"safety"},{"mp_id":88715,"twitter_handle":"karinagould","word_cloud":null,"favourite_word":"region"},{"mp_id":89236,"twitter_handle":"terrybeech","word_cloud":null,"favourite_word":null},{"mp_id":31701,"twitter_handle":"kennedystewart","word_cloud":"autoimg/wordcloud-pol/kennedy-stewart.png","favourite_word":"burnaby"},{"mp_id":89111,"twitter_handle":"kenthehr","word_cloud":null,"favourite_word":"going"},{"mp_id":89116,"twitter_handle":"Webber4Confed","word_cloud":null,"favourite_word":"suicide"},{"mp_id":1287,"twitter_handle":"deepakobhrai","word_cloud":"autoimg/wordcloud-pol/deepak-obhrai.png","favourite_word":"isil"},{"mp_id":1733,"twitter_handle":"stephenharper","word_cloud":"autoimg/wordcloud-pol/stephen-harper.png","favourite_word":"ndp"},{"mp_id":1302,"twitter_handle":"jkenney","word_cloud":"autoimg/wordcloud-pol/jason-kenney.png","favourite_word":"military"},{"mp_id":71902,"twitter_handle":"MichelleRempel","word_cloud":"autoimg/wordcloud-pol/michelle-rempel.png","favourite_word":"refugees"},{"mp_id":89130,"twitter_handle":"PatKelly_MP","word_cloud":null,"favourite_word":"cra"},{"mp_id":89136,"twitter_handle":"tomkmiec","word_cloud":null,"favourite_word":"tax"},{"mp_id":89139,"twitter_handle":"RonLiepert","word_cloud":null,"favourite_word":"budget"},{"mp_id":89144,"twitter_handle":"darshankang","word_cloud":null,"favourite_word":"maybe"},{"mp_id":71599,"twitter_handle":"Bryanmay17","word_cloud":null,"favourite_word":"report"},{"mp_id":1804,"twitter_handle":"RodgerCuzner","word_cloud":"autoimg/wordcloud-pol/rodger-cuzner.png","favourite_word":"number"},{"mp_id":33,"twitter_handle":"L_MacAulay","word_cloud":"autoimg/wordcloud-pol/lawrence-macaulay.png","favourite_word":"fish"},{"mp_id":89249,"twitter_handle":"ToddDohertyMP","word_cloud":null,"favourite_word":"air"},{"mp_id":25524,"twitter_handle":"PierrePoilievre","word_cloud":"autoimg/wordcloud-pol/pierre-poilievre.png","favourite_word":"families"},{"mp_id":59156,"twitter_handle":"KellyBlockmp","word_cloud":"autoimg/wordcloud-pol/kelly-block.png","favourite_word":"air"},{"mp_id":88316,"twitter_handle":"SeanFraserMP","word_cloud":null,"favourite_word":"violence"},{"mp_id":72029,"twitter_handle":"DanAlbas","word_cloud":"autoimg/wordcloud-pol/dan-albas.png","favourite_word":"appreciate"},{"mp_id":71454,"twitter_handle":null,"word_cloud":null,"favourite_word":"isis"},{"mp_id":89027,"twitter_handle":"DougEyolfson","word_cloud":null,"favourite_word":"might"},{"mp_id":71270,"twitter_handle":"SeanCaseyLPC","word_cloud":"autoimg/wordcloud-pol/sean-casey.png","favourite_word":"justice"},{"mp_id":88442,"twitter_handle":"BShanahanLib","word_cloud":null,"favourite_word":"financial"},{"mp_id":31765,"twitter_handle":"DVK_CKL","word_cloud":"autoimg/wordcloud-pol/dave-van-kesteren.png","favourite_word":"something"},{"mp_id":88446,"twitter_handle":"DenisLemieuxLib","word_cloud":null,"favourite_word":"medical"},{"mp_id":71986,"twitter_handle":"markstrahl","word_cloud":"autoimg/wordcloud-pol/mark-strahl.png","favourite_word":"yukon"},{"mp_id":36037,"twitter_handle":"nikiashton","word_cloud":"autoimg/wordcloud-pol/niki-ashton.png","favourite_word":"communities"},{"mp_id":89258,"twitter_handle":"jwaldag","word_cloud":null,"favourite_word":"parks"},{"mp_id":25456,"twitter_handle":"Scott_Simms","word_cloud":"autoimg/wordcloud-pol/scott-simms.png","favourite_word":"particular"},{"mp_id":88449,"twitter_handle":"mclaudebibeau","word_cloud":null,"favourite_word":"international"},{"mp_id":59293,"twitter_handle":"RonMcKinnonLib","word_cloud":null,"favourite_word":"overdose"},{"mp_id":89263,"twitter_handle":"GordJohns","word_cloud":null,"favourite_word":"communities"},{"mp_id":89269,"twitter_handle":"AMacGregor4CML","word_cloud":null,"favourite_word":"liberal"},{"mp_id":51,"twitter_handle":"billcaseyns","word_cloud":null,"favourite_word":"torture"},{"mp_id":1795,"twitter_handle":"DavidAndersonSK","word_cloud":"autoimg/wordcloud-pol/david-anderson.png","favourite_word":"freedom"},{"mp_id":88323,"twitter_handle":"DarrenFisherNS","word_cloud":null,"favourite_word":"chair"},{"mp_id":69488,"twitter_handle":"RobertSopuck","word_cloud":"autoimg/wordcloud-pol/robert-sopuck.png","favourite_word":"environment"},{"mp_id":88721,"twitter_handle":"JulieDzerowicz","word_cloud":null,"favourite_word":"know"},{"mp_id":89272,"twitter_handle":"CQualtro","word_cloud":null,"favourite_word":"athletes"},{"mp_id":89065,"twitter_handle":"GeorginaNDP","word_cloud":null,"favourite_word":"saskatchewan"},{"mp_id":25449,"twitter_handle":"Yasmin_Ratansi","word_cloud":null,"favourite_word":"rcmp"},{"mp_id":88726,"twitter_handle":"GengTanMP","word_cloud":null,"favourite_word":"years"},{"mp_id":58858,"twitter_handle":"Rob_Oliphant","word_cloud":null,"favourite_word":"dementia"},{"mp_id":88453,"twitter_handle":"adhillonMP","word_cloud":null,"favourite_word":"violence"},{"mp_id":35351,"twitter_handle":"F_Choquette","word_cloud":"autoimg/wordcloud-pol/francois-choquette.png","favourite_word":"conservatives"},{"mp_id":25461,"twitter_handle":"davidtilson","word_cloud":"autoimg/wordcloud-pol/david-tilson.png","favourite_word":"chairman"},{"mp_id":72773,"twitter_handle":"ErinOTooleMP","word_cloud":"autoimg/wordcloud-pol/erin-otoole.png","favourite_word":"debate"},{"mp_id":89147,"twitter_handle":"R_Boissonnault","word_cloud":null,"favourite_word":"community"},{"mp_id":89150,"twitter_handle":"KerryDiotte","word_cloud":null,"favourite_word":"transparency"},{"mp_id":89156,"twitter_handle":"ziad4manning","word_cloud":null,"favourite_word":"tax"},{"mp_id":89163,"twitter_handle":"SohiAmarjeet","word_cloud":null,"favourite_word":"communities"},{"mp_id":89167,"twitter_handle":"jeneroux","word_cloud":null,"favourite_word":"something"},{"mp_id":35873,"twitter_handle":"LindaDuncanMP","word_cloud":"autoimg/wordcloud-pol/linda-duncan.png","favourite_word":"alberta"},{"mp_id":89179,"twitter_handle":"KellyMcCauleyMP","word_cloud":null,"favourite_word":"israel"},{"mp_id":35857,"twitter_handle":"MikeLakeMP","word_cloud":"autoimg/wordcloud-pol/mike-lake.png","favourite_word":"businesses"},{"mp_id":88738,"twitter_handle":"marcomendicino","word_cloud":null,"favourite_word":"harassment"},{"mp_id":88308,"twitter_handle":"MorrisseyEgmont","word_cloud":null,"favourite_word":"commons"},{"mp_id":88742,"twitter_handle":"karen_vecchio","word_cloud":null,"favourite_word":"looking"},{"mp_id":89032,"twitter_handle":"Daniel_Blaikie","word_cloud":null,"favourite_word":"rcmp"},{"mp_id":71995,"twitter_handle":"r_garrison","word_cloud":"autoimg/wordcloud-pol/randall-garrison.png","favourite_word":"csis"},{"mp_id":88745,"twitter_handle":"traceyram","word_cloud":null,"favourite_word":"jobs"},{"mp_id":25468,"twitter_handle":"BorysWrz","word_cloud":null,"favourite_word":"forces"},{"mp_id":58877,"twitter_handle":"KirstyDuncanMP","word_cloud":"autoimg/wordcloud-pol/kirsty-duncan.png","favourite_word":"ebola"},{"mp_id":88748,"twitter_handle":"j_maloney","word_cloud":null,"favourite_word":"first"},{"mp_id":31715,"twitter_handle":"DavidSweetMP","word_cloud":"autoimg/wordcloud-pol/david-sweet.png","favourite_word":"hamilton"},{"mp_id":89274,"twitter_handle":"KenHardie","word_cloud":null,"favourite_word":"things"},{"mp_id":86261,"twitter_handle":"JohnBarlowMP","word_cloud":null,"favourite_word":"alberta"},{"mp_id":86260,"twitter_handle":"DavidYurdiga","word_cloud":null,"favourite_word":"communities"}]
